alibabacloud_nlb20220430/__init__.py
alibabacloud_nlb20220430/client.py
alibabacloud_nlb20220430/models/__init__.py
alibabacloud_nlb20220430/models/_add_servers_to_server_group_request.py
alibabacloud_nlb20220430/models/_add_servers_to_server_group_response.py
alibabacloud_nlb20220430/models/_add_servers_to_server_group_response_body.py
alibabacloud_nlb20220430/models/_associate_additional_certificates_with_listener_request.py
alibabacloud_nlb20220430/models/_associate_additional_certificates_with_listener_response.py
alibabacloud_nlb20220430/models/_associate_additional_certificates_with_listener_response_body.py
alibabacloud_nlb20220430/models/_attach_common_bandwidth_package_to_load_balancer_request.py
alibabacloud_nlb20220430/models/_attach_common_bandwidth_package_to_load_balancer_response.py
alibabacloud_nlb20220430/models/_attach_common_bandwidth_package_to_load_balancer_response_body.py
alibabacloud_nlb20220430/models/_cancel_shift_load_balancer_zones_request.py
alibabacloud_nlb20220430/models/_cancel_shift_load_balancer_zones_response.py
alibabacloud_nlb20220430/models/_cancel_shift_load_balancer_zones_response_body.py
alibabacloud_nlb20220430/models/_create_listener_request.py
alibabacloud_nlb20220430/models/_create_listener_response.py
alibabacloud_nlb20220430/models/_create_listener_response_body.py
alibabacloud_nlb20220430/models/_create_listener_shrink_request.py
alibabacloud_nlb20220430/models/_create_load_balancer_request.py
alibabacloud_nlb20220430/models/_create_load_balancer_response.py
alibabacloud_nlb20220430/models/_create_load_balancer_response_body.py
alibabacloud_nlb20220430/models/_create_security_policy_request.py
alibabacloud_nlb20220430/models/_create_security_policy_response.py
alibabacloud_nlb20220430/models/_create_security_policy_response_body.py
alibabacloud_nlb20220430/models/_create_server_group_request.py
alibabacloud_nlb20220430/models/_create_server_group_response.py
alibabacloud_nlb20220430-4.1.2.dist-info/LICENSE
alibabacloud_nlb20220430-4.1.2.dist-info/METADATA
alibabacloud_nlb20220430-4.1.2.dist-info/WHEEL
alibabacloud_nlb20220430-4.1.2.dist-info/top_level.txt
alibabacloud_nlb20220430-4.1.2.dist-info/RECORD
